Metadata-Version: 2.1
Name: temp_email_automa
Version: 0.0.7
Summary: A Python Package to Provide Temp Emails for AUTOMATION!
Home-page: https://github.com/Automa-Automations/temp_email_automa
Author: Simon Ferns
Author-email: business@simonferns.com
License: MIT
Keywords: temp-email automation email
Classifier: Development Status :: 3 - Alpha
Classifier: Intended Audience :: Developers
Classifier: License :: OSI Approved :: MIT License
Classifier: Programming Language :: Python :: 3
Classifier: Programming Language :: Python :: 3.6
Classifier: Programming Language :: Python :: 3.7
Classifier: Programming Language :: Python :: 3.8
Classifier: Programming Language :: Python :: 3.9
Classifier: Operating System :: OS Independent
License-File: LICENCE.txt
Requires-Dist: requests
